bittytax/__init__.py
bittytax/audit.py
bittytax/audit_excel.py
bittytax/bittytax.py
bittytax/bt_types.py
bittytax/config.py
bittytax/constants.py
bittytax/exceptions.py
bittytax/export_records.py
bittytax/holdings.py
bittytax/import_records.py
bittytax/py.typed
bittytax/report.py
bittytax/t_record.py
bittytax/t_row.py
bittytax/tax.py
bittytax/tax_event.py
bittytax/transactions.py
bittytax/utils.py
bittytax/version.py
bittytax/config/bittytax.conf
bittytax/conv/__init__.py
bittytax/conv/bittytax_conv.py
bittytax/conv/datafile.py
bittytax/conv/datamerge.py
bittytax/conv/dataparser.py
bittytax/conv/datarow.py
bittytax/conv/exceptions.py
bittytax/conv/out_record.py
bittytax/conv/output_csv.py
bittytax/conv/output_excel.py
bittytax/conv/mergers/__init__.py
bittytax/conv/mergers/binance.py
bittytax/conv/mergers/coincorner.py
bittytax/conv/mergers/etherscan.py
bittytax/conv/mergers/snowtrace.py
bittytax/conv/parsers/__init__.py
bittytax/conv/parsers/accointing.py
bittytax/conv/parsers/adalite.py
bittytax/conv/parsers/aptoscan.py
bittytax/conv/parsers/barclays.py
bittytax/conv/parsers/binance.py
bittytax/conv/parsers/binance_us.py
bittytax/conv/parsers/bitcointaxes.py
bittytax/conv/parsers/bitfinex.py
bittytax/conv/parsers/bitpanda.py
bittytax/conv/parsers/bitstamp.py
bittytax/conv/parsers/bittrex.py
bittytax/conv/parsers/bittylicious.py
bittytax/conv/parsers/blockchain.py
bittytax/conv/parsers/blockchainexc.py
bittytax/conv/parsers/blockfi.py
bittytax/conv/parsers/blockpit.py
bittytax/conv/parsers/blockscout.py
bittytax/conv/parsers/bnktothefuture.py
bittytax/conv/parsers/bybit.py
bittytax/conv/parsers/cashapp.py
bittytax/conv/parsers/celsius.py
bittytax/conv/parsers/cexio.py
bittytax/conv/parsers/cgtcalculator.py
bittytax/conv/parsers/changelly.py
bittytax/conv/parsers/changetip.py
bittytax/conv/parsers/circle.py
bittytax/conv/parsers/coinbase.py
bittytax/conv/parsers/coinbasepro.py
bittytax/conv/parsers/coincorner.py
bittytax/conv/parsers/coinfloor.py
bittytax-0.6.0.dist-info/licenses/LICENSE
bittytax-0.6.0.dist-info/METADATA
bittytax-0.6.0.dist-info/WHEEL
bittytax-0.6.0.dist-info/entry_points.txt
bittytax-0.6.0.dist-info/top_level.txt
bittytax-0.6.0.dist-info/RECORD
