Metadata-Version: 2.4
Name: BittyTax
Version: 0.6.0
Summary: Crypto-currency tax calculator for UK tax rules. Produces a PDF report of your capital gains and income. Import your data from popular wallets and exchanges.
Home-page: https://github.com/BittyTax/BittyTax
Author: Nano Nano Ltd
Author-email: bittytax@nanonano.co.uk
Maintainer: Scott Green
Maintainer-email: scott.green@nanonano.co.uk
License: AGPLv3
Project-URL: Donate, https://github.com/sponsors/BittyTax
Project-URL: Twitter, https://x.com/bitty_tax
Project-URL: Discord, https://discord.com/invite/NHE3QFt
Project-URL: Changes, https://github.com/BittyTax/BittyTax/blob/master/CHANGELOG.md
Project-URL: Source, https://github.com/BittyTax/BittyTax
Project-URL: Tracker, https://github.com/BittyTax/BittyTax/issues
Keywords: bittytax cryptoasset cryptocurrency cryptotax
Classifier: Development Status :: 5 - Production/Stable
Classifier: Environment :: Console
Classifier: Intended Audience :: End Users/Desktop
Classifier: Topic :: Office/Business :: Financial :: Accounting
Classifier: License :: OSI Approved :: GNU Affero General Public License v3
Classifier: Natural Language :: English
Classifier: Operating System :: MacOS
Classifier: Operating System :: Microsoft :: Windows
Classifier: Operating System :: POSIX :: Linux
Classifier: Programming Language :: Python :: 3.7
Classifier: Programming Language :: Python :: 3.8
Classifier: Programming Language :: Python :: 3.9
Classifier: Programming Language :: Python :: 3.10
Classifier: Programming Language :: Python :: 3.11
Classifier: Programming Language :: Python :: 3.12
Classifier: Programming Language :: Python :: 3.13
Classifier: Programming Language :: Python :: 3.14
Requires-Python: >=3.7
License-File: LICENSE
Requires-Dist: colorama
Requires-Dist: defusedxml
Requires-Dist: importlib-resources; python_version < "3.9"
Requires-Dist: jinja2
Requires-Dist: openpyxl
Requires-Dist: python-dateutil
Requires-Dist: pyyaml
Requires-Dist: requests
Requires-Dist: setuptools>=71.1
Requires-Dist: typing_extensions>=4.1.0
Requires-Dist: tqdm
Requires-Dist: xhtml2pdf
Requires-Dist: xlrd
Requires-Dist: xlsxwriter>=3.0.6
Provides-Extra: dev
Requires-Dist: isort; extra == "dev"
Requires-Dist: black; extra == "dev"
Requires-Dist: flake8; extra == "dev"
Requires-Dist: pylint; extra == "dev"
Requires-Dist: pyenchant; extra == "dev"
Requires-Dist: djlint; extra == "dev"
Requires-Dist: mypy; extra == "dev"
Requires-Dist: pytest; extra == "dev"
Dynamic: license-file
